ai_error_handler/__init__.py
ai_error_handler/api.py
ai_error_handler/error_explainer.py
ai_error_handler/logger.py
ai_error_handler/webapi.py
ai_error_handler-0.1.1.dist-info/licenses/LICENSE
ai_error_handler-0.1.1.dist-info/METADATA
ai_error_handler-0.1.1.dist-info/WHEEL
ai_error_handler-0.1.1.dist-info/top_level.txt
ai_error_handler-0.1.1.dist-info/RECORD
