Metadata-Version: 2.4
Name: ai-error-handler
Version: 0.1.1
Summary: A Python package for AI-based error handling.
Home-page: https://github.com/Avi-lapulga/ai-error-handler
Author: REDPENCIL
Author-email: redpencil2025@gmail.com
Classifier: Programming Language :: Python :: 3
Classifier: License :: OSI Approved :: MIT License
Classifier: Operating System :: OS Independent
Requires-Python: >=3.8
License-File: LICENSE
Requires-Dist: llama-cpp-python
Requires-Dist: fastapi
Requires-Dist: uvicorn
Dynamic: author
Dynamic: author-email
Dynamic: classifier
Dynamic: description
Dynamic: description-content-type
Dynamic: home-page
Dynamic: license-file
Dynamic: requires-dist
Dynamic: requires-python
Dynamic: summary
